setup.py
memcpu/__init__.py
memcpu.egg-info/PKG-INFO
memcpu.egg-info/SOURCES.txt
memcpu.egg-info/dependency_links.txt
memcpu.egg-info/not-zip-safe
memcpu.egg-info/top_level.txt