Metadata-Version: 1.0
Name: memcpu
Version: 0.1
Summary: The world
Home-page: https://www.memcpu.com/
Author: zqian
Author-email: zqian@memcpu.com
License: MIT
Platform: UNKNOWN
